berry/__init__.py
berry/__main__.py
berry/cli.py
stups_berry-1.0.28.dist-info/DESCRIPTION.rst
stups_berry-1.0.28.dist-info/METADATA
stups_berry-1.0.28.dist-info/RECORD
stups_berry-1.0.28.dist-info/WHEEL
stups_berry-1.0.28.dist-info/entry_points.txt
stups_berry-1.0.28.dist-info/metadata.json
stups_berry-1.0.28.dist-info/top_level.txt
