Metadata-Version: 2.0
Name: stups-berry
Version: 1.0.28
Summary: Credentials distribution agent
Home-page: https://github.com/zalando-stups/berry
Author: Henning Jacobs
Author-email: henning.jacobs@zalando.de
License: Apache License 2.0
Keywords: credentials distribution aws s3 stups
Platform: UNKNOWN
Classifier: Development Status :: 4 - Beta
Classifier: Environment :: Console
Classifier: Intended Audience :: System Administrators
Classifier: License :: OSI Approved :: Apache Software License
Classifier: Operating System :: POSIX :: Linux
Classifier: Programming Language :: Python
Classifier: Programming Language :: Python :: 2.7
Classifier: Programming Language :: Python :: 3.4
Classifier: Programming Language :: Python :: Implementation :: CPython
Requires-Dist: PyYAML
Requires-Dist: boto3 (>=1.2.3)
Requires-Dist: dnspython (>=1.15.0)
